{
	"routes": [
		{
			"method": "GET",
			"path": "/sample-authenticated-views",
			"handler": "sample-authenticated-views.find",
			"config": {
				"policies": []
			}
		},
		{
			"method": "GET",
			"path": "/sample-authenticated-views/count",
			"handler": "sample-authenticated-views.count",
			"config": {
				"policies": []
			}
		},
		{
			"method": "GET",
			"path": "/sample-authenticated-views/:id",
			"handler": "sample-authenticated-views.findOne",
			"config": {
				"policies": []
			}
		},
		{
			"method": "POST",
			"path": "/sample-authenticated-views",
			"handler": "sample-authenticated-views.create",
			"config": {
				"policies": []
			}
		},
		{
			"method": "PUT",
			"path": "/sample-authenticated-views/:id",
			"handler": "sample-authenticated-views.update",
			"config": {
				"policies": []
			}
		},
		{
			"method": "DELETE",
			"path": "/sample-authenticated-views/:id",
			"handler": "sample-authenticated-views.delete",
			"config": {
				"policies": []
			}
		}
	]
}
